ninja_apikey/__init__.py
ninja_apikey/admin.py
ninja_apikey/apps.py
ninja_apikey/models.py
ninja_apikey/security.py
ninja_apikey/tests.py
ninja_apikey/migrations/0001_initial.py
ninja_apikey/migrations/__init__.py
django_ninja_apikey-0.2.1.dist-info/LICENSE
django_ninja_apikey-0.2.1.dist-info/WHEEL
django_ninja_apikey-0.2.1.dist-info/METADATA
django_ninja_apikey-0.2.1.dist-info/RECORD
